model_forge_llm-2.3.0.dist-info/licenses/LICENSE
modelforge/__init__.py
modelforge/auth.py
modelforge/cli.py
modelforge/config.py
modelforge/enhanced_llm.py
modelforge/exceptions.py
modelforge/logging_config.py
modelforge/modelsdev.py
modelforge/registry.py
modelforge/retry.py
modelforge/streaming.py
modelforge/telemetry.py
modelforge/validation.py
modelforge/wizard.py
model_forge_llm-2.3.0.dist-info/METADATA
model_forge_llm-2.3.0.dist-info/WHEEL
model_forge_llm-2.3.0.dist-info/entry_points.txt
model_forge_llm-2.3.0.dist-info/top_level.txt
model_forge_llm-2.3.0.dist-info/RECORD
