Metadata-Version: 2.4
Name: model-forge-llm
Version: 2.3.0
Summary: A reusable library for managing LLM providers, authentication, and model selection.
Author: ModelForge Contributors
License: MIT License
Project-URL: Homepage, https://github.com/smiao-icims/model-forge
Project-URL: Repository, https://github.com/smiao-icims/model-forge
Project-URL: Issues, https://github.com/smiao-icims/model-forge/issues
Project-URL: Documentation, https://model-forge.readthedocs.io
Keywords: llm,ai,langchain,openai,ollama,providers,authentication
Classifier: Development Status :: 4 - Beta
Classifier: Intended Audience :: Developers
Classifier: License :: OSI Approved :: MIT License
Classifier: Operating System :: OS Independent
Classifier: Programming Language :: Python :: 3
Classifier: Programming Language :: Python :: 3.11
Classifier: Programming Language :: Python :: 3.12
Classifier: Topic :: Software Development :: Libraries :: Python Modules
Classifier: Topic :: Scientific/Engineering :: Artificial Intelligence
Requires-Python: <4.0,>=3.11
License-File: LICENSE
Requires-Dist: click>=8.1.7
Requires-Dist: questionary>=2.0.0
Requires-Dist: requests>=2.32.3
Requires-Dist: langchain-core>=0.3.0
Requires-Dist: langchain-openai>=0.3.0
Requires-Dist: langchain-community>=0.3.0
Requires-Dist: langchain-google-genai>=2.1.5
Requires-Dist: langchain-github-copilot>=0.4.0
Provides-Extra: dev
Requires-Dist: pytest>=8.2.2; extra == "dev"
Requires-Dist: pytest-mock>=3.14.0; extra == "dev"
Requires-Dist: ruff>=0.7.0; extra == "dev"
Requires-Dist: mypy>=1.11.0; extra == "dev"
Requires-Dist: pre-commit>=3.8.0; extra == "dev"
Requires-Dist: pytest-cov>=5.0.0; extra == "dev"
Requires-Dist: types-requests>=2.32.0; extra == "dev"
Requires-Dist: twine>=6.1.0; extra == "dev"
Requires-Dist: requests-mock>=1.12.1; extra == "dev"
Dynamic: license-file
